{
    "num_classes": 38,
    "class_to_idx": {
        "crown": 0,
        "hilux": 1,
        "vitz": 2,
        "hiace": 3,
        "corona": 4,
        "aygo": 5,
        "avanza": 6,
        "4runner": 7,
        "vios": 8,
        "sequoia": 9,
        "avensis": 10,
        "supra": 11,
        "sienna": 12,
        "etios": 13,
        "prius": 14,
        "rush": 15,
        "previa": 16,
        "innova": 17,
        "highlander": 18,
        "revo": 19,
        "tacoma": 20,
        "alphard": 21,
        "starlet": 22,
        "mirai": 23,
        "tundra": 24,
        "venza": 25,
        "yaris": 26,
        "iq": 27,
        "estima": 28,
        "soarer": 29,
        "verso": 30,
        "matrix": 31,
        "camry": 32,
        "avalon": 33,
        "rav4": 34,
        "celica": 35,
        "corolla": 36,
        "fortuner": 37
    }
}